debugscribe/__init__.py
debugscribe/main.py
debugscribe/prompts.py
debugscribe-2025.12.21165719.dist-info/METADATA
debugscribe-2025.12.21165719.dist-info/WHEEL
debugscribe-2025.12.21165719.dist-info/top_level.txt
debugscribe-2025.12.21165719.dist-info/RECORD
