Metadata-Version: 2.4
Name: debugscribe
Version: 2025.12.21165719
Summary: A new package designed to assist users in understanding and resolving errors in program execution. Users can input error messages or descriptions of unexpected program behavior, and the package will u
Author-email: debugscribe <hi@eugene.plus>
License: MIT
Project-URL: Homepage, https://github.com/chigwell/debugscribe
Requires-Python: >=3.9
Requires-Dist: langchain-llm7>=0.0.0
Requires-Dist: llmatch-messages>=0.0.0
Requires-Dist: langchain-core>=0.3.0
